{
  "title": "Artisan Marketplace Delhi",
  "slug": "artisan-marketplace-delhi",
  "category": "commercial",
  "location": "Connaught Place, Delhi",
  "client_name": "Artisan Heritage Group",
  "testimonial": "This isn't just a marketplace — it's a celebration of Indian craftsmanship. Foot traffic exceeded projections by 140%, and we've become a cultural landmark in Delhi.",
  "description": "10,000 sq ft multi-brand artisan marketplace showcasing 45+ Indian craftspeople and design collectives. Features modular vendor stalls with heritage finishes, a central interactive workshop space, expert-curated gallery zones, and a 100-seat tasting area for specialty foods. Designed to evolve with rotating installations.",
  "year": 2023,
  "area": "10,000 sq ft",
  "duration": "18 weeks",
  "featured": false,
  "tags": ["Retail Marketplace", "Heritage Design", "Modular Systems", "Cultural Space", "Community Focus"],
  "placeholder_images": [
    "https://picsum.photos/seed/artisan-market-1/1200/800",
    "https://picsum.photos/seed/artisan-market-2/1200/800",
    "https://picsum.photos/seed/artisan-market-3/1200/800",
    "https://picsum.photos/seed/artisan-market-4/1200/800"
  ],
  "cover_image": "https://picsum.photos/seed/artisan-market-1/1200/800"
}
